repo_mapper/__init__.py
repo_mapper/__main__.py
repo_mapper_py/__init__.py
repo_mapper_py/repo_mapper_py.cpython-312-x86_64-linux-gnu.so
repo_mapper_rs-0.4.0.dist-info/METADATA
repo_mapper_rs-0.4.0.dist-info/WHEEL
repo_mapper_rs-0.4.0.dist-info/licenses/LICENSE
repo_mapper_rs-0.4.0.dist-info/RECORD
