Metadata-Version: 2.4
Name: repo-mapper-rs
Version: 0.4.0
Classifier: Programming Language :: Rust
Classifier: Programming Language :: Python :: Implementation :: CPython
Classifier: Programming Language :: Python :: Implementation :: PyPy
License-File: LICENSE
License-Expression: MIT
Requires-Python: >=3.10
